ExAssist/__init__.py
ExAssist/assist.py
ExAssist/host_info.py
ExAssist/template.py
ExAssist/templates/.DS_Store
ExAssist/templates/ex.html
ExAssist/templates/index.html
ExAssist/templates/css/bootstrap-grid.css
ExAssist/templates/css/bootstrap-grid.css.map
ExAssist/templates/css/bootstrap-grid.min.css
ExAssist/templates/css/bootstrap-grid.min.css.map
ExAssist/templates/css/bootstrap-grid.rtl.css
ExAssist/templates/css/bootstrap-grid.rtl.css.map
ExAssist/templates/css/bootstrap-grid.rtl.min.css
ExAssist/templates/css/bootstrap-grid.rtl.min.css.map
ExAssist/templates/css/bootstrap-reboot.css
ExAssist/templates/css/bootstrap-reboot.css.map
ExAssist/templates/css/bootstrap-reboot.min.css
ExAssist/templates/css/bootstrap-reboot.min.css.map
ExAssist/templates/css/bootstrap-reboot.rtl.css
ExAssist/templates/css/bootstrap-reboot.rtl.css.map
ExAssist/templates/css/bootstrap-reboot.rtl.min.css
ExAssist/templates/css/bootstrap-reboot.rtl.min.css.map
ExAssist/templates/css/bootstrap-utilities.css
ExAssist/templates/css/bootstrap-utilities.css.map
ExAssist/templates/css/bootstrap-utilities.min.css
ExAssist/templates/css/bootstrap-utilities.min.css.map
ExAssist/templates/css/bootstrap-utilities.rtl.css
ExAssist/templates/css/bootstrap-utilities.rtl.css.map
ExAssist/templates/css/bootstrap-utilities.rtl.min.css
ExAssist/templates/css/bootstrap-utilities.rtl.min.css.map
ExAssist/templates/css/bootstrap.css
ExAssist/templates/css/bootstrap.css.map
ExAssist/templates/css/bootstrap.min.css
ExAssist/templates/css/bootstrap.min.css.map
ExAssist/templates/css/bootstrap.rtl.css
ExAssist/templates/css/bootstrap.rtl.css.map
ExAssist/templates/css/bootstrap.rtl.min.css
ExAssist/templates/css/bootstrap.rtl.min.css.map
ExAssist/templates/js/.DS_Store
ExAssist/templates/js/Chart.js
ExAssist/templates/js/bootstrap.bundle.js
ExAssist/templates/js/bootstrap.bundle.js.map
ExAssist/templates/js/bootstrap.bundle.min.js
ExAssist/templates/js/bootstrap.bundle.min.js.map
ExAssist-0.3.6.dist-info/LICENSE
ExAssist-0.3.6.dist-info/METADATA
ExAssist-0.3.6.dist-info/WHEEL
ExAssist-0.3.6.dist-info/top_level.txt
ExAssist-0.3.6.dist-info/RECORD
