Metadata-Version: 2.1
Name: ExAssist
Version: 0.3.6
Summary: Experiment Assist
Home-page: https://github.com/flyaway1217/ExAssist
Author: Flyaway
Author-email: flyaway1217@gmail.com
License: GPL
Keywords: Experiment Assist
Platform: UNKNOWN
Requires-Dist: Mako (>=1.0.7)
